pci_lib/__init__.py
pci_lib/pci_lib.py
pci_vpd_lib/__init__.py
pci_vpd_lib/pci_vpd_lib.py
pcicrawler/__init__.py
pcicrawler/__version__.py
pcicrawler/cli.py
pcicrawler-1.0.0.dist-info/LICENSE
pcicrawler-1.0.0.dist-info/METADATA
pcicrawler-1.0.0.dist-info/WHEEL
pcicrawler-1.0.0.dist-info/entry_points.txt
pcicrawler-1.0.0.dist-info/top_level.txt
pcicrawler-1.0.0.dist-info/RECORD
