Metadata-Version: 2.1
Name: pcicrawler
Version: 1.0.0
Summary: Open source tool to display/filter/export information about PCI or PCI Express devices, as well as their topology.
Home-page: https://github.com/facebook/pcicrawler
Author: Ashwin Poojary
Author-email: ashwinp@fb.com
License: MIT
Platform: UNKNOWN
Requires-Python: >=3.6.0
Requires-Dist: click
Requires-Dist: six
